stduritemplate/__init__.py
stduritemplate/py.typed
std_uritemplate-2.0.7.dist-info/METADATA
std_uritemplate-2.0.7.dist-info/WHEEL
std_uritemplate-2.0.7.dist-info/RECORD
