Metadata-Version: 2.4
Name: std-uritemplate
Version: 2.0.7
Summary: std-uritemplate implementation for Python
License: Apache-2.0
Keywords: std-uritemplate,uritemplate,uritemplates,stduritemplate
Author: Andrea Peruffo
Author-email: andrea.peruffo1982@gmail.com
Requires-Python: >=3.8,<4.0
Classifier: License :: OSI Approved :: Apache Software License
Classifier: Programming Language :: Python :: 3
Classifier: Programming Language :: Python :: 3.8
Classifier: Programming Language :: Python :: 3.9
Classifier: Programming Language :: Python :: 3.10
Classifier: Programming Language :: Python :: 3.11
Classifier: Programming Language :: Python :: 3.12
Classifier: Programming Language :: Python :: 3.13
Classifier: Programming Language :: Python :: 3.14
Project-URL: Homepage, https://github.com/std-uritemplate/std-uritemplate
Project-URL: Repository, https://github.com/std-uritemplate/std-uritemplate
